[
{"created_at":"Mon, 13 May 2013 09:05:41 +0000","id_str":"333870651960086528","text":"Richtig! ~&gt; DSL: Straßen-Demo für freies Internet http://t.co/rgfxfDTNxy #Telekom #Aufschrei #Wissen #News","entities":{"user_mentions":[],"hashtags":[{"indices":[76,84],"text":"Telekom"},{"indices":[85,95],"text":"Aufschrei"},{"indices":[96,103],"text":"Wissen"},{"indices":[104,109],"text":"News"}],"urls":[{"url":"http://t.co/rgfxfDTNxy","indices":[53,75],"expanded_url":"http://buff.ly/15wsp6r","display_url":"buff.ly/15wsp6r"}]},"user":{"name":"Coachforyou","id_str":"21750314","id":21750314,"screen_name":"Coachforyou","profile_image_url_https":"https://si0.twimg.com/profile_images/83506492/Nidi-Solo400_normal.jpg","profile_image_url":"http://a0.twimg.com/profile_images/83506492/Nidi-Solo400_normal.jpg"},"source":"&lt;a href=&quot;http://www.hootsuite.com&quot;&gt;HootSuite&lt;/a&gt;"},
{"created_at":"Mon, 13 May 2013 08:54:52 +0000","id_str":"333867931966509056","text":"RT @CKlausing: Der reaktionäre Account @tatortwatch verzichtet auf #Gendergap bzw. #Genderstar und reproduziert so bipolare Geschlechtlichkeit. #aufschrei","entities":{"user_mentions":[{"id":29947731,"indices":[3,13],"id_str":"29947731","screen_name":"CKlausing","name":"Christoph Klausing"},{"id":1417354207,"indices":[39,51],"id_str":"1417354207","screen_name":"TatortWatch","name":"Darf der Tatort das?"}],"hashtags":[{"indices":[67,77],"text":"Gendergap"},{"indices":[83,94],"text":"Genderstar"},{"indices":[144,154],"text":"aufschrei"}],"urls":[]},"user":{"name":"Luca Leitterstorf","id_str":"305633775","id":305633775,"screen_name":"titusluca","profile_image_url_https":"https://si0.twimg.com/profile_images/2626771602/1cux0xk366iq2qnrt3zf_normal.jpeg","profile_image_url":"http://a0.twimg.com/profile_images/2626771602/1cux0xk366iq2qnrt3zf_normal.jpeg"},"source":"&lt;a href=&quot;http://twitter.com/download/iphone&quot;&gt;Twitter for iPhone&lt;/a&gt;"},
{"created_at":"Mon, 13 May 2013 08:48:35 +0000","id_str":"333866350428696576","text":"@zoradebrunner stelle fest: wenn es um Pflichten geht, ist es mit der Gleichberechtigung ganz schnell wieder vorbei. #Aufschrei!","entities":{"user_mentions":[{"id":49996637,"indices":[0,14],"id_str":"49996637","screen_name":"zoradebrunner","name":"die nähdrescherin"}],"hashtags":[{"indices":[117,127],"text":"Aufschrei"}],"urls":[]},"user":{"name":"Mestre Tirador","id_str":"968360580","id":968360580,"screen_name":"sanglier0815","profile_image_url_https":"https://si0.twimg.com/profile_images/3646286054/c1cfee820680a27a53af786f3ac986d6_normal.jpeg","profile_image_url":"http://a0.twimg.com/profile_images/3646286054/c1cfee820680a27a53af786f3ac986d6_normal.jpeg"},"in_reply_to_status_id_str":"333860719487492096","source":"&lt;a href=&quot;http://twitter.com/download/android&quot;&gt;Twitter for Android&lt;/a&gt;"},
{"created_at":"Mon, 13 May 2013 08:47:55 +0000","id_str":"333866183180812289","text":"RT @_Marie_Kuhn: @Puretruth678 Und hinterher wird dann ein #aufschrei-Inszeniert, weil sie nie gewählt werden und -na klar - eine Quote gefordert.","entities":{"user_mentions":[{"id":1143444648,"indices":[3,15],"id_str":"1143444648","screen_name":"_Marie_Kuhn","name":"Marie Kuhn"},{"id":1337504312,"indices":[17,30],"id_str":"1337504312","screen_name":"Puretruth678","name":"Thomas Bayer "}],"hashtags":[{"indices":[59,69],"text":"aufschrei"}],"urls":[]},"user":{"name":"@aufschrei_watch","id_str":"1415573677","id":1415573677,"screen_name":"aufschrei_watch","profile_image_url_https":"https://si0.twimg.com/profile_images/3635491633/404307629a2cb2438da05fbcedf72585_normal.jpeg","profile_image_url":"http://a0.twimg.com/profile_images/3635491633/404307629a2cb2438da05fbcedf72585_normal.jpeg"},"in_reply_to_status_id_str":"333811514333097984","source":"&lt;a href=&quot;http://twitter.com/&quot;&gt;web&lt;/a&gt;"},
{"created_at":"Mon, 13 May 2013 08:47:01 +0000","id_str":"333865957611151360","text":"RT @sarahemily_11: Schlagzeile from Hell! RT “@GNetzer: Meine Fresse, BILD... #aufschrei http://t.co/NNJwTDYTiB”","entities":{"user_mentions":[{"id":47981483,"indices":[3,17],"id_str":"47981483","screen_name":"sarahemily_11","name":"sarahemily"},{"id":16064783,"indices":[46,54],"id_str":"16064783","screen_name":"GNetzer","name":"Max-Jacob Ost"}],"media":[{"source_status_id_str":"333526539658477568","expanded_url":"http://twitter.com/GNetzer/status/333526539658477568/photo/1","display_url":"pic.twitter.com/NNJwTDYTiB","url":"http://t.co/NNJwTDYTiB","media_url_https":"https://pbs.twimg.com/media/BKDsnufCQAAJz6C.png","source_status_id":333526539658477600,"id_str":"333526539662671872","sizes":{"large":{"h":372,"resize":"fit","w":659},"small":{"h":192,"resize":"fit","w":340},"medium":{"h":339,"resize":"fit","w":600},"thumb":{"h":150,"resize":"crop","w":150},"orig":{"h":372,"resize":"fit","w":659}},"indices":[89,111],"type":"photo","id":333526539662671900,"media_url":"http://pbs.twimg.com/media/BKDsnufCQAAJz6C.png"}],"hashtags":[{"indices":[78,88],"text":"aufschrei"}],"urls":[]},"user":{"name":"AnwohnerIniSchanze","id_str":"302576057","id":302576057,"screen_name":"SchanzenINI","profile_image_url_https":"https://si0.twimg.com/profile_images/2936250622/9b43285f7cbe04ec367819669219cb99_normal.png","profile_image_url":"http://a0.twimg.com/profile_images/2936250622/9b43285f7cbe04ec367819669219cb99_normal.png"},"in_reply_to_status_id_str":"333526539658477568","source":"&lt;a href=&quot;http://www.tweetdeck.com&quot;&gt;TweetDeck&lt;/a&gt;"},
{"created_at":"Mon, 13 May 2013 08:44:44 +0000","id_str":"333865381301190656","text":"RT @Berufszyniker16: @Lesegefahr Ich tippe auf #Mangel an #Kritikfähigkeit u Drang zu #Vertuschung, dass mehr als 90% von #aufschrei gelogen ist.","entities":{"user_mentions":[{"id":1338434784,"indices":[3,19],"id_str":"1338434784","screen_name":"Berufszyniker16","name":"Berufszyniker.com"},{"id":286071368,"indices":[21,32],"id_str":"286071368","screen_name":"Lesegefahr","name":"Martin Häberle"}],"hashtags":[{"indices":[47,54],"text":"Mangel"},{"indices":[58,74],"text":"Kritikfähigkeit"},{"indices":[86,98],"text":"Vertuschung"},{"indices":[122,132],"text":"aufschrei"}],"urls":[]},"user":{"name":"@aufschrei_watch","id_str":"1415573677","id":1415573677,"screen_name":"aufschrei_watch","profile_image_url_https":"https://si0.twimg.com/profile_images/3635491633/404307629a2cb2438da05fbcedf72585_normal.jpeg","profile_image_url":"http://a0.twimg.com/profile_images/3635491633/404307629a2cb2438da05fbcedf72585_normal.jpeg"},"in_reply_to_status_id_str":"333571360947310592","source":"&lt;a href=&quot;http://twitter.com/&quot;&gt;web&lt;/a&gt;"},
{"created_at":"Mon, 13 May 2013 08:43:05 +0000","id_str":"333864965859577856","text":"RT @sarahemily_11: Schlagzeile from Hell! RT “@GNetzer: Meine Fresse, BILD... #aufschrei http://t.co/NNJwTDYTiB”","entities":{"user_mentions":[{"id":47981483,"indices":[3,17],"id_str":"47981483","screen_name":"sarahemily_11","name":"sarahemily"},{"id":16064783,"indices":[46,54],"id_str":"16064783","screen_name":"GNetzer","name":"Max-Jacob Ost"}],"media":[{"source_status_id_str":"333526539658477568","expanded_url":"http://twitter.com/GNetzer/status/333526539658477568/photo/1","display_url":"pic.twitter.com/NNJwTDYTiB","url":"http://t.co/NNJwTDYTiB","media_url_https":"https://pbs.twimg.com/media/BKDsnufCQAAJz6C.png","source_status_id":333526539658477600,"id_str":"333526539662671872","sizes":{"large":{"h":372,"resize":"fit","w":659},"small":{"h":192,"resize":"fit","w":340},"medium":{"h":339,"resize":"fit","w":600},"thumb":{"h":150,"resize":"crop","w":150},"orig":{"h":372,"resize":"fit","w":659}},"indices":[89,111],"type":"photo","id":333526539662671900,"media_url":"http://pbs.twimg.com/media/BKDsnufCQAAJz6C.png"}],"hashtags":[{"indices":[78,88],"text":"aufschrei"}],"urls":[]},"user":{"name":"@aufschrei_watch","id_str":"1415573677","id":1415573677,"screen_name":"aufschrei_watch","profile_image_url_https":"https://si0.twimg.com/profile_images/3635491633/404307629a2cb2438da05fbcedf72585_normal.jpeg","profile_image_url":"http://a0.twimg.com/profile_images/3635491633/404307629a2cb2438da05fbcedf72585_normal.jpeg"},"in_reply_to_status_id_str":"333526539658477568","source":"&lt;a href=&quot;http://twitter.com/&quot;&gt;web&lt;/a&gt;"},
{"created_at":"Mon, 13 May 2013 08:41:24 +0000","id_str":"333864543040176129","text":"RT @SPM11Plus: „Die #Frauen haben sich entwickelt in den letzten Jahren...#Lothar's ganz eigene Sicht der Dinge #zitate #aufschrei http://t.co/IMVlX31wGc","entities":{"user_mentions":[{"id":944266003,"indices":[3,13],"id_str":"944266003","screen_name":"SPM11Plus","name":"SportManagement 11+"}],"media":[{"expanded_url":"http://twitter.com/SPM11Plus/status/333507251312680960/photo/1","display_url":"pic.twitter.com/IMVlX31wGc","url":"http://t.co/IMVlX31wGc","media_url_https":"https://pbs.twimg.com/media/BKDbE_0CYAAgGg0.jpg","id_str":"333507251321069568","sizes":{"small":{"h":87,"resize":"fit","w":340},"large":{"h":239,"resize":"fit","w":933},"medium":{"h":154,"resize":"fit","w":600},"thumb":{"h":150,"resize":"crop","w":150},"orig":{"h":239,"resize":"fit","w":933}},"indices":[131,153],"type":"photo","id":333507251321069600,"media_url":"http://pbs.twimg.com/media/BKDbE_0CYAAgGg0.jpg"}],"hashtags":[{"indices":[20,27],"text":"Frauen"},{"indices":[74,81],"text":"Lothar"},{"indices":[112,119],"text":"zitate"},{"indices":[120,130],"text":"aufschrei"}],"urls":[]},"user":{"name":"@aufschrei_watch","id_str":"1415573677","id":1415573677,"screen_name":"aufschrei_watch","profile_image_url_https":"https://si0.twimg.com/profile_images/3635491633/404307629a2cb2438da05fbcedf72585_normal.jpeg","profile_image_url":"http://a0.twimg.com/profile_images/3635491633/404307629a2cb2438da05fbcedf72585_normal.jpeg"},"source":"&lt;a href=&quot;http://twitter.com/&quot;&gt;web&lt;/a&gt;"},
{"created_at":"Mon, 13 May 2013 08:38:00 +0000","id_str":"333863688580780032","text":"Hätte Sammer oder Heynckes solche Aussagen getroffen  #Aufschrei #Klopp","entities":{"user_mentions":[],"hashtags":[{"indices":[54,64],"text":"Aufschrei"},{"indices":[65,71],"text":"Klopp"}],"urls":[]},"user":{"name":"Marco Werner","id_str":"720921228","id":720921228,"screen_name":"schnumbi","profile_image_url_https":"https://si0.twimg.com/profile_images/3636730901/1aa8f065058f9a248306ce2ca07cc2a4_normal.png","profile_image_url":"http://a0.twimg.com/profile_images/3636730901/1aa8f065058f9a248306ce2ca07cc2a4_normal.png"},"source":"&lt;a href=&quot;http://twitter.com/&quot;&gt;web&lt;/a&gt;"},
{"created_at":"Mon, 13 May 2013 08:36:54 +0000","id_str":"333863409068150784","text":"RT @SaschiHalefOmar: @Michaelsen_J Sexismus ist es anscheinend nur, wenn Frauen betroffen sind. Diese #Aufschrei-Debatte ist scheinheilig. http://t.co/q5tdOrHEBE","entities":{"user_mentions":[{"id":1275692563,"indices":[3,19],"id_str":"1275692563","screen_name":"SaschiHalefOmar","name":"Saschi Halef Omar"},{"id":555796109,"indices":[21,34],"id_str":"555796109","screen_name":"Michaelsen_J","name":"jeannine michaelsen"}],"hashtags":[{"indices":[102,112],"text":"Aufschrei"}],"urls":[{"url":"http://t.co/q5tdOrHEBE","indices":[139,161],"expanded_url":"http://bit.ly/10zV6HJ","display_url":"bit.ly/10zV6HJ"}]},"user":{"name":"@aufschrei_watch","id_str":"1415573677","id":1415573677,"screen_name":"aufschrei_watch","profile_image_url_https":"https://si0.twimg.com/profile_images/3635491633/404307629a2cb2438da05fbcedf72585_normal.jpeg","profile_image_url":"http://a0.twimg.com/profile_images/3635491633/404307629a2cb2438da05fbcedf72585_normal.jpeg"},"in_reply_to_status_id_str":"322279429902569472","source":"&lt;a href=&quot;http://twitter.com/&quot;&gt;web&lt;/a&gt;"},
{"created_at":"Mon, 13 May 2013 08:36:21 +0000","id_str":"333863270475767808","text":"RT @besterwosgibt: \"What can I do to make you happy?\" #aufschrei http://t.co/Tt5eptNbu7","entities":{"user_mentions":[{"id":14585651,"indices":[3,17],"id_str":"14585651","screen_name":"besterwosgibt","name":"Dominic"}],"media":[{"expanded_url":"http://twitter.com/besterwosgibt/status/333283103286112256/photo/1","display_url":"pic.twitter.com/Tt5eptNbu7","url":"http://t.co/Tt5eptNbu7","media_url_https":"https://pbs.twimg.com/media/BKAPN3VCMAEspay.jpg","id_str":"333283103290306561","sizes":{"small":{"h":284,"resize":"fit","w":340},"large":{"h":417,"resize":"fit","w":500},"medium":{"h":417,"resize":"fit","w":500},"thumb":{"h":150,"resize":"crop","w":150},"orig":{"h":417,"resize":"fit","w":500}},"indices":[65,87],"type":"photo","id":333283103290306560,"media_url":"http://pbs.twimg.com/media/BKAPN3VCMAEspay.jpg"}],"hashtags":[{"indices":[54,64],"text":"aufschrei"}],"urls":[]},"user":{"name":"@aufschrei_watch","id_str":"1415573677","id":1415573677,"screen_name":"aufschrei_watch","profile_image_url_https":"https://si0.twimg.com/profile_images/3635491633/404307629a2cb2438da05fbcedf72585_normal.jpeg","profile_image_url":"http://a0.twimg.com/profile_images/3635491633/404307629a2cb2438da05fbcedf72585_normal.jpeg"},"source":"&lt;a href=&quot;http://twitter.com/&quot;&gt;web&lt;/a&gt;"},
{"created_at":"Mon, 13 May 2013 08:36:01 +0000","id_str":"333863186006683648","text":"RT @Mariquita2013: Männer beim Sport, die sich neben mir darüber unterhalten, dass der männliche Schwellkörper im Gegensatz zum Körper nicht altert #aufschrei","entities":{"user_mentions":[{"id":1230715213,"indices":[3,17],"id_str":"1230715213","screen_name":"Mariquita2013","name":"Mariquita"}],"hashtags":[{"indices":[148,158],"text":"aufschrei"}],"urls":[]},"user":{"name":"@aufschrei_watch","id_str":"1415573677","id":1415573677,"screen_name":"aufschrei_watch","profile_image_url_https":"https://si0.twimg.com/profile_images/3635491633/404307629a2cb2438da05fbcedf72585_normal.jpeg","profile_image_url":"http://a0.twimg.com/profile_images/3635491633/404307629a2cb2438da05fbcedf72585_normal.jpeg"},"source":"&lt;a href=&quot;http://twitter.com/&quot;&gt;web&lt;/a&gt;"},
{"created_at":"Mon, 13 May 2013 08:34:38 +0000","id_str":"333862838194020352","text":"RT @WagnerSolms1971: Skandalös! \"@RolandTichy: FAZ meldet, dass Männermodells weniger verdienen als weibliche. #Aufschrei\"","entities":{"user_mentions":[{"id":171759364,"indices":[3,19],"id_str":"171759364","screen_name":"WagnerSolms1971","name":"ThorstenTHECAT"},{"id":19962363,"indices":[33,45],"id_str":"19962363","screen_name":"RolandTichy","name":"Roland Tichy"}],"hashtags":[{"indices":[111,121],"text":"Aufschrei"}],"urls":[]},"user":{"name":"@aufschrei_watch","id_str":"1415573677","id":1415573677,"screen_name":"aufschrei_watch","profile_image_url_https":"https://si0.twimg.com/profile_images/3635491633/404307629a2cb2438da05fbcedf72585_normal.jpeg","profile_image_url":"http://a0.twimg.com/profile_images/3635491633/404307629a2cb2438da05fbcedf72585_normal.jpeg"},"source":"&lt;a href=&quot;http://twitter.com/&quot;&gt;web&lt;/a&gt;"},
{"created_at":"Mon, 13 May 2013 08:31:36 +0000","id_str":"333862077624102912","text":"Die \"Wirtschaftswoche\" vermeldet \"Genderirrsinn\" und sieht \"Auswüchse\": http://t.co/W26Or1sP3W #aufschrei @wiwo","entities":{"user_mentions":[{"id":19709133,"indices":[106,111],"id_str":"19709133","screen_name":"wiwo","name":"WirtschaftsWoche"}],"hashtags":[{"indices":[95,105],"text":"aufschrei"}],"urls":[{"url":"http://t.co/W26Or1sP3W","indices":[72,94],"expanded_url":"http://www.wiwo.de/erfolg/trends/genderirrsinn-skurrile-unfaelle-im-kampf-gegen-den-sexismus/8131180.html","display_url":"wiwo.de/erfolg/trends/…"}]},"user":{"name":"@aufschrei_watch","id_str":"1415573677","id":1415573677,"screen_name":"aufschrei_watch","profile_image_url_https":"https://si0.twimg.com/profile_images/3635491633/404307629a2cb2438da05fbcedf72585_normal.jpeg","profile_image_url":"http://a0.twimg.com/profile_images/3635491633/404307629a2cb2438da05fbcedf72585_normal.jpeg"},"source":"&lt;a href=&quot;http://twitter.com/&quot;&gt;web&lt;/a&gt;"},
{"created_at":"Mon, 13 May 2013 08:12:12 +0000","id_str":"333857192631484416","text":"RT @Missy_Magazine: Wir vergeben 2 Abos! Schreibt uns unter #Aufschrei_Talk was wir die legendäre Angela McRobbie am 20.5 bei unserem Talk im HAU fragen sollen!","entities":{"user_mentions":[{"id":38717515,"indices":[3,18],"id_str":"38717515","screen_name":"Missy_Magazine","name":"Missy Magazine"}],"hashtags":[{"indices":[60,75],"text":"Aufschrei_Talk"}],"urls":[]},"user":{"name":"Ninia LaGrande","id_str":"151353021","id":151353021,"screen_name":"NiniaLaGrande","profile_image_url_https":"https://si0.twimg.com/profile_images/3474531877/7771de9dc062baabd829fb529ae7b66d_normal.png","profile_image_url":"http://a0.twimg.com/profile_images/3474531877/7771de9dc062baabd829fb529ae7b66d_normal.png"},"source":"&lt;a href=&quot;http://twitter.com/&quot;&gt;web&lt;/a&gt;"},
{"created_at":"Mon, 13 May 2013 08:06:08 +0000","id_str":"333855669298024448","text":"Wir vergeben 2 Abos! Schreibt uns unter #Aufschrei_Talk was wir die legendäre Angela McRobbie am 20.5 bei unserem Talk im HAU fragen sollen!","entities":{"user_mentions":[],"hashtags":[{"indices":[40,55],"text":"Aufschrei_Talk"}],"urls":[]},"user":{"name":"Missy Magazine","id_str":"38717515","id":38717515,"screen_name":"Missy_Magazine","profile_image_url_https":"https://si0.twimg.com/profile_images/3630129725/20103b5e9a136ad1df44e36ce850ccc0_normal.jpeg","profile_image_url":"http://a0.twimg.com/profile_images/3630129725/20103b5e9a136ad1df44e36ce850ccc0_normal.jpeg"},"source":"&lt;a href=&quot;http://twitter.com/&quot;&gt;web&lt;/a&gt;"},
{"created_at":"Mon, 13 May 2013 08:03:34 +0000","id_str":"333855022439862272","text":"RT @CKlausing: Der reaktionäre Account @tatortwatch verzichtet auf #Gendergap bzw. #Genderstar und reproduziert so bipolare Geschlechtlichkeit. #aufschrei","entities":{"user_mentions":[{"id":29947731,"indices":[3,13],"id_str":"29947731","screen_name":"CKlausing","name":"Christoph Klausing"},{"id":1417354207,"indices":[39,51],"id_str":"1417354207","screen_name":"TatortWatch","name":"Darf der Tatort das?"}],"hashtags":[{"indices":[67,77],"text":"Gendergap"},{"indices":[83,94],"text":"Genderstar"},{"indices":[144,154],"text":"aufschrei"}],"urls":[]},"user":{"name":"Benjamin Thomas","id_str":"75113916","id":75113916,"screen_name":"BenjaminDThomas","profile_image_url_https":"https://si0.twimg.com/profile_images/1157603532/49069_1661793260_4109_q_normal.jpg","profile_image_url":"http://a0.twimg.com/profile_images/1157603532/49069_1661793260_4109_q_normal.jpg"},"source":"&lt;a href=&quot;http://twitter.com/download/android&quot;&gt;Twitter for Android&lt;/a&gt;"},
{"created_at":"Mon, 13 May 2013 08:02:28 +0000","id_str":"333854745108299777","text":"RT @CKlausing: Der reaktionäre Account @tatortwatch verzichtet auf #Gendergap bzw. #Genderstar und reproduziert so bipolare Geschlechtlichkeit. #aufschrei","entities":{"user_mentions":[{"id":29947731,"indices":[3,13],"id_str":"29947731","screen_name":"CKlausing","name":"Christoph Klausing"},{"id":1417354207,"indices":[39,51],"id_str":"1417354207","screen_name":"TatortWatch","name":"Darf der Tatort das?"}],"hashtags":[{"indices":[67,77],"text":"Gendergap"},{"indices":[83,94],"text":"Genderstar"},{"indices":[144,154],"text":"aufschrei"}],"urls":[]},"user":{"name":"Junge Union Köln","id_str":"35460844","id":35460844,"screen_name":"JU_Koeln","profile_image_url_https":"https://si0.twimg.com/profile_images/1762383238/twitterpicJU_normal.JPG","profile_image_url":"http://a0.twimg.com/profile_images/1762383238/twitterpicJU_normal.JPG"},"source":"&lt;a href=&quot;http://twitter.com/download/iphone&quot;&gt;Twitter for iPhone&lt;/a&gt;"},
{"created_at":"Mon, 13 May 2013 08:01:09 +0000","id_str":"333854414408392705","text":"@Puretruth678 Und hinterher wird dann ein #aufschrei-Inszeniert, weil sie nie gewählt werden und -na klar - eine Quote gefordert.","entities":{"user_mentions":[{"id":1337504312,"indices":[0,13],"id_str":"1337504312","screen_name":"Puretruth678","name":"Thomas Bayer "}],"hashtags":[{"indices":[42,52],"text":"aufschrei"}],"urls":[]},"user":{"name":"Marie Kuhn","id_str":"1143444648","id":1143444648,"screen_name":"_Marie_Kuhn","profile_image_url_https":"https://si0.twimg.com/profile_images/3544161787/ff1cae6874888694cb348934dac30252_normal.png","profile_image_url":"http://a0.twimg.com/profile_images/3544161787/ff1cae6874888694cb348934dac30252_normal.png"},"in_reply_to_status_id_str":"333811514333097984","source":"&lt;a href=&quot;http://twitter.com/&quot;&gt;web&lt;/a&gt;"},
{"created_at":"Mon, 13 May 2013 08:01:08 +0000","id_str":"333854411048767488","text":"Der reaktionäre Account @tatortwatch verzichtet auf #Gendergap bzw. #Genderstar und reproduziert so bipolare Geschlechtlichkeit. #aufschrei","entities":{"user_mentions":[{"id":1417354207,"indices":[24,36],"id_str":"1417354207","screen_name":"TatortWatch","name":"Darf der Tatort das?"}],"hashtags":[{"indices":[52,62],"text":"Gendergap"},{"indices":[68,79],"text":"Genderstar"},{"indices":[129,139],"text":"aufschrei"}],"urls":[]},"user":{"name":"Christoph Klausing","id_str":"29947731","id":29947731,"screen_name":"CKlausing","profile_image_url_https":"https://si0.twimg.com/profile_images/3230042432/f69d634dfe7eee18644b65c242252b0a_normal.jpeg","profile_image_url":"http://a0.twimg.com/profile_images/3230042432/f69d634dfe7eee18644b65c242252b0a_normal.jpeg"},"source":"&lt;a href=&quot;http://twitter.com/download/iphone&quot;&gt;Twitter for iPhone&lt;/a&gt;"},
{"created_at":"Mon, 13 May 2013 07:56:53 +0000","id_str":"333853341333483520","text":"#Aufschrei: Was von der Twitter-Aktion gegen Alltagssexismus bleibt http://t.co/s9u8dYDgc7 (via @SPIEGELONLINE) #rp13","entities":{"user_mentions":[{"id":2834511,"indices":[96,110],"id_str":"2834511","screen_name":"SPIEGELONLINE","name":"SPIEGEL ONLINE"}],"hashtags":[{"indices":[0,10],"text":"Aufschrei"},{"indices":[112,117],"text":"rp13"}],"urls":[{"url":"http://t.co/s9u8dYDgc7","indices":[68,90],"expanded_url":"http://spon.de/adV0u","display_url":"spon.de/adV0u"}]},"user":{"name":"Jan Bartels","id_str":"44113262","id":44113262,"screen_name":"Jan_Bartels","profile_image_url_https":"https://si0.twimg.com/profile_images/1387261457/sing_ding_normal.jpg","profile_image_url":"http://a0.twimg.com/profile_images/1387261457/sing_ding_normal.jpg"},"source":"&lt;a href=&quot;http://www.tweetdeck.com&quot;&gt;TweetDeck&lt;/a&gt;"},
{"created_at":"Mon, 13 May 2013 07:18:19 +0000","id_str":"333843633944002560","text":"RT @MRetsum: @an_fi @walzbar @miinaaa #Feministinnen im \"God Mode\": Diskussion oder gar widersprechen zwecklos. #Aufschrei","entities":{"user_mentions":[{"id":1150907562,"indices":[3,11],"id_str":"1150907562","screen_name":"MRetsum","name":"Familienfundi"},{"id":51217554,"indices":[13,19],"id_str":"51217554","screen_name":"an_fi","name":"o_O"},{"id":714679388,"indices":[20,28],"id_str":"714679388","screen_name":"walzbar","name":"salzbar"},{"id":22057279,"indices":[29,37],"id_str":"22057279","screen_name":"miinaaa","name":"Mina Dingens."}],"hashtags":[{"indices":[38,52],"text":"Feministinnen"},{"indices":[112,122],"text":"Aufschrei"}],"urls":[]},"user":{"name":"Ch. Bauer-Jelinek","id_str":"1148244852","id":1148244852,"screen_name":"BauerJelinek","profile_image_url_https":"https://si0.twimg.com/profile_images/3208396689/c81107fcafe0d5cd2dbeb49fce758484_normal.jpeg","profile_image_url":"http://a0.twimg.com/profile_images/3208396689/c81107fcafe0d5cd2dbeb49fce758484_normal.jpeg"},"in_reply_to_status_id_str":"333841507880677377","source":"&lt;a href=&quot;http://twitter.com/download/iphone&quot;&gt;Twitter for iPhone&lt;/a&gt;"},
{"created_at":"Mon, 13 May 2013 07:15:33 +0000","id_str":"333842936359972864","text":"@an_fi @walzbar @miinaaa #Feministinnen im \"God Mode\": Diskussion oder gar widersprechen zwecklos. #Aufschrei","entities":{"user_mentions":[{"id":51217554,"indices":[0,6],"id_str":"51217554","screen_name":"an_fi","name":"o_O"},{"id":714679388,"indices":[7,15],"id_str":"714679388","screen_name":"walzbar","name":"salzbar"},{"id":22057279,"indices":[16,24],"id_str":"22057279","screen_name":"miinaaa","name":"Mina Dingens."}],"hashtags":[{"indices":[25,39],"text":"Feministinnen"},{"indices":[99,109],"text":"Aufschrei"}],"urls":[]},"user":{"name":"Familienfundi","id_str":"1150907562","id":1150907562,"screen_name":"MRetsum","profile_image_url_https":"https://si0.twimg.com/sticky/default_profile_images/default_profile_0_normal.png","profile_image_url":"http://a0.twimg.com/sticky/default_profile_images/default_profile_0_normal.png"},"in_reply_to_status_id_str":"333841507880677377","source":"&lt;a href=&quot;http://twitter.com/&quot;&gt;web&lt;/a&gt;"},
{"created_at":"Mon, 13 May 2013 07:13:34 +0000","id_str":"333842437594300416","text":"RT @Der_Kalle: Ich bring das jetzt analog zum Aufbau nochmal, egal wie viele entfolgen:Wie viele Frauen helfen grad noch beim Abbau mit? #bpt131 #aufschrei","entities":{"user_mentions":[{"id":32183563,"indices":[3,13],"id_str":"32183563","screen_name":"Der_Kalle","name":"Der Kalle"}],"hashtags":[{"indices":[137,144],"text":"bpt131"},{"indices":[145,155],"text":"aufschrei"}],"urls":[]},"user":{"name":"Peter, Pirat","id_str":"455152811","id":455152811,"screen_name":"PiratPeter","profile_image_url_https":"https://si0.twimg.com/profile_images/3574354256/93d7f23c9161547051d6c936699c3741_normal.jpeg","profile_image_url":"http://a0.twimg.com/profile_images/3574354256/93d7f23c9161547051d6c936699c3741_normal.jpeg"},"source":"&lt;a href=&quot;http://twitter.com/&quot;&gt;web&lt;/a&gt;"},
{"created_at":"Mon, 13 May 2013 07:06:49 +0000","id_str":"333840739136049152","text":"#Aufschrei: #Postgender fordern, aber auf Geschlechtsspezifika rumreiten: #Mädchenmannschaft, #Frauenquote, #FEMINismus, ...","entities":{"user_mentions":[],"hashtags":[{"indices":[0,10],"text":"Aufschrei"},{"indices":[12,23],"text":"Postgender"},{"indices":[74,92],"text":"Mädchenmannschaft"},{"indices":[94,106],"text":"Frauenquote"},{"indices":[108,119],"text":"FEMINismus"}],"urls":[]},"user":{"name":"Familienfundi","id_str":"1150907562","id":1150907562,"screen_name":"MRetsum","profile_image_url_https":"https://si0.twimg.com/sticky/default_profile_images/default_profile_0_normal.png","profile_image_url":"http://a0.twimg.com/sticky/default_profile_images/default_profile_0_normal.png"},"source":"&lt;a href=&quot;http://twitter.com/&quot;&gt;web&lt;/a&gt;"},
{"created_at":"Mon, 13 May 2013 06:45:20 +0000","id_str":"333835332736917504","text":"#seehofer #muttertag #aufschrei http://t.co/TUJrlUDP2s","entities":{"user_mentions":[],"hashtags":[{"indices":[0,9],"text":"seehofer"},{"indices":[10,20],"text":"muttertag"},{"indices":[21,31],"text":"aufschrei"}],"urls":[{"url":"http://t.co/TUJrlUDP2s","indices":[32,54],"expanded_url":"http://www.spiegel.de/spiegel/vorab/chef-der-bundesnetzagentur-wegen-top-personalie-in-erklaerungsnot-a-899263.html","display_url":"spiegel.de/spiegel/vorab/…"}]},"user":{"name":"Die Rechtsanwaeldin","id_str":"160812512","id":160812512,"screen_name":"Rechtsanwaeldin","profile_image_url_https":"https://si0.twimg.com/profile_images/2818567792/0ed048f3e8142cc413483e6a2df61644_normal.png","profile_image_url":"http://a0.twimg.com/profile_images/2818567792/0ed048f3e8142cc413483e6a2df61644_normal.png"},"source":"&lt;a href=&quot;http://twitter.com/&quot;&gt;web&lt;/a&gt;"},
{"created_at":"Mon, 13 May 2013 06:43:01 +0000","id_str":"333834750705954816","text":"Schwedische Feministin: breitbeinig sitzende Männer führen zu Vergewaltigungen http://t.co/SraTRtyCfD #aufschrei durchgeknallt","entities":{"user_mentions":[],"hashtags":[{"indices":[102,112],"text":"aufschrei"}],"urls":[{"url":"http://t.co/SraTRtyCfD","indices":[79,101],"expanded_url":"http://www.netreaper.net/2013/04/04/schwedische-feministin-breitbeinig-sitzende-manner-fuhren-zu-vergewaltigungen/","display_url":"netreaper.net/2013/04/04/sch…"}]},"user":{"name":"django","id_str":"43736987","id":43736987,"screen_name":"cherubimu","profile_image_url_https":"https://si0.twimg.com/profile_images/1213138305/cherubimu2011_klein_normal.jpg","profile_image_url":"http://a0.twimg.com/profile_images/1213138305/cherubimu2011_klein_normal.jpg"},"source":"&lt;a href=&quot;http://twitter.com/&quot;&gt;web&lt;/a&gt;"},
{"created_at":"Mon, 13 May 2013 06:40:08 +0000","id_str":"333834023099052032","text":"@LinaMadita @Stereolino Genau, so viel heiße #Luft u so viele #Lügen u #Manipulationen hinter #aufschrei #storytelling #kampagne","entities":{"user_mentions":[{"id":73966120,"indices":[0,11],"id_str":"73966120","screen_name":"LinaMadita","name":"Lina Madita "},{"id":962671963,"indices":[12,23],"id_str":"962671963","screen_name":"Stereolino","name":"Jean "}],"hashtags":[{"indices":[45,50],"text":"Luft"},{"indices":[62,68],"text":"Lügen"},{"indices":[71,86],"text":"Manipulationen"},{"indices":[94,104],"text":"aufschrei"},{"indices":[105,118],"text":"storytelling"},{"indices":[119,128],"text":"kampagne"}],"urls":[]},"user":{"name":"Berufszyniker.com","id_str":"1338434784","id":1338434784,"screen_name":"Berufszyniker16","profile_image_url_https":"https://si0.twimg.com/sticky/default_profile_images/default_profile_1_normal.png","profile_image_url":"http://a0.twimg.com/sticky/default_profile_images/default_profile_1_normal.png"},"in_reply_to_status_id_str":"333833230451085312","source":"&lt;a href=&quot;http://twitter.com/&quot;&gt;web&lt;/a&gt;"},
{"created_at":"Mon, 13 May 2013 06:35:57 +0000","id_str":"333832973990379520","text":"#Frauen werden überbewertet.... #Männer auch... #aufschrei","entities":{"user_mentions":[],"hashtags":[{"indices":[0,7],"text":"Frauen"},{"indices":[32,39],"text":"Männer"},{"indices":[48,58],"text":"aufschrei"}],"urls":[]},"user":{"name":"Michael Nickel","id_str":"23069883","id":23069883,"screen_name":"micleftic","profile_image_url_https":"https://si0.twimg.com/profile_images/2045878635/398712_2979877589190_1629441180_2505466_1613518371_n_normal.jpg","profile_image_url":"http://a0.twimg.com/profile_images/2045878635/398712_2979877589190_1629441180_2505466_1613518371_n_normal.jpg"},"source":"&lt;a href=&quot;http://twitter.com/download/android&quot;&gt;Twitter for Android&lt;/a&gt;"},
{"created_at":"Mon, 13 May 2013 06:30:39 +0000","id_str":"333831639119585280","text":"@LinaMadita der Kabelträger eben war ein Mann! #aufschrei","entities":{"user_mentions":[{"id":73966120,"indices":[0,11],"id_str":"73966120","screen_name":"LinaMadita","name":"Lina Madita "}],"hashtags":[{"indices":[47,57],"text":"aufschrei"}],"urls":[]},"user":{"name":"Jean ","id_str":"962671963","id":962671963,"screen_name":"Stereolino","profile_image_url_https":"https://si0.twimg.com/profile_images/2880416792/6764030504dbc116d2fd01be962a8f08_normal.jpeg","profile_image_url":"http://a0.twimg.com/profile_images/2880416792/6764030504dbc116d2fd01be962a8f08_normal.jpeg"},"in_reply_to_status_id_str":"333830495345442816","source":"&lt;a href=&quot;http://getfalcon.pro&quot;&gt;Falcon Pro&lt;/a&gt;"},
{"created_at":"Mon, 13 May 2013 06:17:45 +0000","id_str":"333828389842583552","text":"Aufräumen im postpatriarchalen Durcheinander http://t.co/FZhYIYtDPy #BGE #aufschrei #Entdualisierung","entities":{"user_mentions":[],"hashtags":[{"indices":[68,72],"text":"BGE"},{"indices":[73,83],"text":"aufschrei"},{"indices":[84,100],"text":"Entdualisierung"}],"urls":[{"url":"http://t.co/FZhYIYtDPy","indices":[45,67],"expanded_url":"http://abcdesgutenlebens.wordpress.com","display_url":"abcdesgutenlebens.wordpress.com"}]},"user":{"name":"Ina Praetorius","id_str":"405472617","id":405472617,"screen_name":"InaPraetorius","profile_image_url_https":"https://si0.twimg.com/profile_images/1623518246/DSC08840_normal.JPG","profile_image_url":"http://a0.twimg.com/profile_images/1623518246/DSC08840_normal.JPG"},"source":"&lt;a href=&quot;http://twitter.com/&quot;&gt;web&lt;/a&gt;"},
{"created_at":"Mon, 13 May 2013 06:14:16 +0000","id_str":"333827515573485570","text":"RT @RolandTichy: FAZ meldet, dass Männermodells weniger verdienen als weibliche. #Aufschrei","entities":{"user_mentions":[{"id":19962363,"indices":[3,15],"id_str":"19962363","screen_name":"RolandTichy","name":"Roland Tichy"}],"hashtags":[{"indices":[81,91],"text":"Aufschrei"}],"urls":[]},"user":{"name":"iWoWaSays","id_str":"128226138","id":128226138,"screen_name":"iWoWaSays","profile_image_url_https":"https://si0.twimg.com/profile_images/943902611/4btEkgp4UNbX4T6edKYc5lpA_normal.jpg","profile_image_url":"http://a0.twimg.com/profile_images/943902611/4btEkgp4UNbX4T6edKYc5lpA_normal.jpg"},"source":"&lt;a href=&quot;http://twicca.r246.jp/&quot;&gt;twicca&lt;/a&gt;"},
{"created_at":"Mon, 13 May 2013 06:11:51 +0000","id_str":"333826905864290304","text":"@Coladewe @miiiezekatze @jazz_mazz @HulkPunch #Aufschrei","entities":{"user_mentions":[{"id":169137290,"indices":[0,9],"id_str":"169137290","screen_name":"Coladewe","name":"Zimtarella"},{"id":78352829,"indices":[10,23],"id_str":"78352829","screen_name":"miiiezekatze","name":"traumflauschmuschi"},{"id":93436748,"indices":[24,34],"id_str":"93436748","screen_name":"jazz_mazz","name":"Jazz Morgan"},{"id":1373937632,"indices":[35,45],"id_str":"1373937632","screen_name":"HulkPunch","name":"Bruce Banner"}],"hashtags":[{"indices":[46,56],"text":"Aufschrei"}],"urls":[]},"user":{"name":"mostly harmless","id_str":"158656607","id":158656607,"screen_name":"NikSput","profile_image_url_https":"https://si0.twimg.com/profile_images/3061000947/fca0244da15ca43bd87202f9da11114c_normal.jpeg","profile_image_url":"http://a0.twimg.com/profile_images/3061000947/fca0244da15ca43bd87202f9da11114c_normal.jpeg"},"in_reply_to_status_id_str":"333823321789579264","source":"&lt;a href=&quot;http://tapbots.com/tweetbot&quot;&gt;Tweetbot for iOS&lt;/a&gt;"},
{"created_at":"Mon, 13 May 2013 05:41:45 +0000","id_str":"333819334063435776","text":"Wenn heute 100 % Frauen das #moma im @ZDF wuppen, sollte es dann nicht eigentlich #mama heißen? Den #Aufschrei liefere ich gleich mit... ;-)","entities":{"user_mentions":[{"id":57350105,"indices":[37,41],"id_str":"57350105","screen_name":"ZDF","name":"ZDF"}],"hashtags":[{"indices":[28,33],"text":"moma"},{"indices":[82,87],"text":"mama"},{"indices":[100,110],"text":"Aufschrei"}],"urls":[]},"user":{"name":"tknews","id_str":"19937279","id":19937279,"screen_name":"tknews","profile_image_url_https":"https://si0.twimg.com/profile_images/74882185/15052006114_normal.jpg","profile_image_url":"http://a0.twimg.com/profile_images/74882185/15052006114_normal.jpg"},"source":"&lt;a href=&quot;http://twitter.com/download/android&quot;&gt;Twitter for Android&lt;/a&gt;"},
{"created_at":"Mon, 13 May 2013 05:10:41 +0000","id_str":"333811514333097984","text":"\"Grüne wollen Miss-Wahl auch für weniger Schöne. \" Warum nicht auch übergewichtige 50 jährige mit Holzbein zulassen?  #Grüne  #Aufschrei","entities":{"user_mentions":[],"hashtags":[{"indices":[118,124],"text":"Grüne"},{"indices":[126,136],"text":"Aufschrei"}],"urls":[]},"user":{"name":"Thomas Bayer ","id_str":"1337504312","id":1337504312,"screen_name":"Puretruth678","profile_image_url_https":"https://si0.twimg.com/sticky/default_profile_images/default_profile_4_normal.png","profile_image_url":"http://a0.twimg.com/sticky/default_profile_images/default_profile_4_normal.png"},"source":"&lt;a href=&quot;http://ubersocial.com&quot;&gt;UberSocial for Android&lt;/a&gt;"},
{"created_at":"Mon, 13 May 2013 04:59:41 +0000","id_str":"333808745417154560","text":"Morgensonne, Kaffee, @marthadear-Int. für #voxpublica schneiden - und die Frage: was ist eure Bilanz zu #Aufschrei?-&gt; http://t.co/KVjHTo7aLg","entities":{"user_mentions":[{"id":13745852,"indices":[21,32],"id_str":"13745852","screen_name":"marthadear","name":"anne wizorek"}],"hashtags":[{"indices":[42,53],"text":"voxpublica"},{"indices":[104,114],"text":"Aufschrei"}],"urls":[{"url":"http://t.co/KVjHTo7aLg","indices":[121,143],"expanded_url":"http://ow.ly/kTJzv","display_url":"ow.ly/kTJzv"}]},"user":{"name":"marcus engert","id_str":"331598085","id":331598085,"screen_name":"marcusengert","profile_image_url_https":"https://si0.twimg.com/profile_images/3382867166/ba847df8c07316e26fef5282c5e97ff1_normal.jpeg","profile_image_url":"http://a0.twimg.com/profile_images/3382867166/ba847df8c07316e26fef5282c5e97ff1_normal.jpeg"},"source":"&lt;a href=&quot;http://twitter.com/download/android&quot;&gt;Twitter for Android&lt;/a&gt;"},
{"created_at":"Mon, 13 May 2013 00:31:22 +0000","id_str":"333741219534487552","text":"RT @Der_Kalle: Ich bring das jetzt analog zum Aufbau nochmal, egal wie viele entfolgen:Wie viele Frauen helfen grad noch beim Abbau mit? #bpt131 #aufschrei","entities":{"user_mentions":[{"id":32183563,"indices":[3,13],"id_str":"32183563","screen_name":"Der_Kalle","name":"Der Kalle"}],"hashtags":[{"indices":[137,144],"text":"bpt131"},{"indices":[145,155],"text":"aufschrei"}],"urls":[]},"user":{"name":"Thoralf Will","id_str":"19069715","id":19069715,"screen_name":"umrath","profile_image_url_https":"https://si0.twimg.com/profile_images/3587019156/f426ff39280e097bd9ff51f8aaed75e0_normal.jpeg","profile_image_url":"http://a0.twimg.com/profile_images/3587019156/f426ff39280e097bd9ff51f8aaed75e0_normal.jpeg"},"source":"&lt;a href=&quot;http://www.tweetcaster.com&quot;&gt;TweetCaster for Android&lt;/a&gt;"},
{"created_at":"Sun, 12 May 2013 23:58:37 +0000","id_str":"333732978159136769","text":"RT @Der_Kalle: Ich bring das jetzt analog zum Aufbau nochmal, egal wie viele entfolgen:Wie viele Frauen helfen grad noch beim Abbau mit? #bpt131 #aufschrei","entities":{"user_mentions":[{"id":32183563,"indices":[3,13],"id_str":"32183563","screen_name":"Der_Kalle","name":"Der Kalle"}],"hashtags":[{"indices":[137,144],"text":"bpt131"},{"indices":[145,155],"text":"aufschrei"}],"urls":[]},"user":{"name":"Andreas Witte","id_str":"87825530","id":87825530,"screen_name":"3811015","profile_image_url_https":"https://si0.twimg.com/profile_images/1512061476/44759775-9ed0-42ef-a7d9-33d35f66877d_normal.png","profile_image_url":"http://a0.twimg.com/profile_images/1512061476/44759775-9ed0-42ef-a7d9-33d35f66877d_normal.png"},"source":"&lt;a href=&quot;http://twitter.com/&quot;&gt;web&lt;/a&gt;"},
{"created_at":"Sun, 12 May 2013 23:56:25 +0000","id_str":"333732426339741696","text":"Ich bring das jetzt analog zum Aufbau nochmal, egal wie viele entfolgen:Wie viele Frauen helfen grad noch beim Abbau mit? #bpt131 #aufschrei","entities":{"user_mentions":[],"hashtags":[{"indices":[122,129],"text":"bpt131"},{"indices":[130,140],"text":"aufschrei"}],"urls":[]},"user":{"name":"Der Kalle","id_str":"32183563","id":32183563,"screen_name":"Der_Kalle","profile_image_url_https":"https://si0.twimg.com/profile_images/3521806214/ca7c4c75f577d77b5d82b2466cd73190_normal.jpeg","profile_image_url":"http://a0.twimg.com/profile_images/3521806214/ca7c4c75f577d77b5d82b2466cd73190_normal.jpeg"},"source":"&lt;a href=&quot;http://mobileways.de/gravity&quot;&gt;Gravity!&lt;/a&gt;"},
{"created_at":"Sun, 12 May 2013 23:29:35 +0000","id_str":"333725672025501698","text":"@spasskultur Na da haben wir ja die Ursache für den #aufschrei:Zu wenig Sauerstoff im Kopf...Kommt sicher von der verstärkten Schnappatmung","entities":{"user_mentions":[{"id":67412123,"indices":[0,12],"id_str":"67412123","screen_name":"spasskultur","name":"spasskultur"}],"hashtags":[{"indices":[52,62],"text":"aufschrei"}],"urls":[]},"user":{"name":"Marie Kuhn","id_str":"1143444648","id":1143444648,"screen_name":"_Marie_Kuhn","profile_image_url_https":"https://si0.twimg.com/profile_images/3544161787/ff1cae6874888694cb348934dac30252_normal.png","profile_image_url":"http://a0.twimg.com/profile_images/3544161787/ff1cae6874888694cb348934dac30252_normal.png"},"in_reply_to_status_id_str":"333642513720160256","source":"&lt;a href=&quot;http://twitter.com/&quot;&gt;web&lt;/a&gt;"}
]
